expandingnet/NN.py
expandingnet/__init__
expandingnet-0.0.4.dist-info/METADATA
expandingnet-0.0.4.dist-info/WHEEL
expandingnet-0.0.4.dist-info/licenses/LICENSE
expandingnet-0.0.4.dist-info/RECORD
