Metadata-Version: 2.4
Name: expandingnet
Version: 0.0.4
Summary: ExpandingNet is a new data driven neural network
Project-URL: Homepage, https://github.com/kaikerochaalves/ExpandingNet.git
Project-URL: Issues, https://github.com/kaikerochaalves/ExpandingNet.git
Author-email: Kaike Sa Teles Rocha Alves <kaikerochaalves@outlook.com>
License-File: LICENSE
Classifier: License :: OSI Approved :: GNU General Public License v3 (GPLv3)
Classifier: Programming Language :: Python :: 3
Requires-Python: >=3.0
Requires-Dist: matplotlib
Requires-Dist: numpy
Requires-Dist: scikit-learn
Requires-Dist: torch
Requires-Dist: torchaudio
Requires-Dist: torchvision
